cf_perfeval/__init__.py
cf_perfeval/helpers.py
cf_perfeval/interaction_views.py
cf_perfeval/library.py
cf_perfeval/views.py
cf_perfeval/visualization_views.py
cf_perfeval/package_data/categories/ed2728bc-3fd5-4244-9876-f6a757d1b922.json
cf_perfeval/package_data/widgets/0b604a1d-f188-4e74-bcda-188829c507c0.json
cf_perfeval/package_data/widgets/17cf3814-1edd-4c0c-84dd-e1198c033584.json
cf_perfeval/package_data/widgets/3564589a-1dea-4743-8a56-d04992d569e8.json
cf_perfeval/package_data/widgets/4098a678-2d14-4cbe-808d-2d150a7c2341.json
cf_perfeval/package_data/widgets/4c667e7a-82fe-4dc3-8f70-48fc261e0eee.json
cf_perfeval/package_data/widgets/5b52c563-3302-429f-9232-4f003e8c11f0.json
cf_perfeval/package_data/widgets/9b6d7a11-1bd9-41b6-ac6d-343fcf31ee1e.json
cf_perfeval/package_data/widgets/b69fff35-ae30-4708-a6ce-7b9cec28e2a9.json
cf_perfeval/static/cf_perfeval/icons/treeview/Bar-chart-icon.png
cf_perfeval/static/cf_perfeval/icons/treeview/Evaluate.png
cf_perfeval/static/cf_perfeval/icons/treeview/EvaluateRepeated.png
cf_perfeval/static/cf_perfeval/icons/treeview/aggregate-icon.png
cf_perfeval/static/cf_perfeval/icons/treeview/construction_work .png
cf_perfeval/static/cf_perfeval/icons/treeview/results-table.png
cf_perfeval/static/cf_perfeval/icons/treeview/viper600-60.png
cf_perfeval/static/cf_perfeval/icons/treeview/viper600-60_1.png
cf_perfeval/static/cf_perfeval/icons/widget/Bar-chart-icon.png
cf_perfeval/static/cf_perfeval/icons/widget/Evaluate.png
cf_perfeval/static/cf_perfeval/icons/widget/EvaluateRepeated.png
cf_perfeval/static/cf_perfeval/icons/widget/aggregate-icon.png
cf_perfeval/static/cf_perfeval/icons/widget/results-table.png
cf_perfeval/static/cf_perfeval/icons/widget/viper600-60.png
cf_perfeval/static/cf_perfeval/icons/widget/viper600-60_1.png
cf_perfeval/static/cf_perfeval/js/highcharts-2.2.5-tooltip-id.js
cf_perfeval/static/cf_perfeval/js/highcharts-exporting.js
cf_perfeval/static/cf_perfeval/js/jquery-1.7.1.min.js
cf_perfeval-0.2.dist-info/DESCRIPTION.rst
cf_perfeval-0.2.dist-info/METADATA
cf_perfeval-0.2.dist-info/RECORD
cf_perfeval-0.2.dist-info/WHEEL
cf_perfeval-0.2.dist-info/metadata.json
cf_perfeval-0.2.dist-info/top_level.txt
