Metadata-Version: 2.0
Name: cf-perfeval
Version: 0.2
Summary: Package providing performance evaluation utilities and widgets for ClowdFlows 3.0
Home-page: https://github.com/xflows/cf_perfeval
Author: Borut Sluban
Author-email: UNKNOWN
License: MIT License
Platform: UNKNOWN
Classifier: Development Status :: 5 - Production/Stable
Classifier: Intended Audience :: Developers
Classifier: Intended Audience :: Science/Research
